LICENSE
MANIFEST.in
README.rst
requirements.txt
setup.py
src/rms2dfinder/__init__.py
src/rms2dfinder/rms2dfinder.py
src/rms2dfinder.egg-info/PKG-INFO
src/rms2dfinder.egg-info/SOURCES.txt
src/rms2dfinder.egg-info/dependency_links.txt
src/rms2dfinder.egg-info/entry_points.txt
src/rms2dfinder.egg-info/requires.txt
src/rms2dfinder.egg-info/top_level.txt
src/rms2dfinder.egg-info/zip-safe