Metadata-Version: 1.1
Name: rms2dfinder
Version: 0.1.0
Summary: A helper utility to find minimum mean RMSd structures of clusters found in rms2d plot.
Home-page: https://github.com/lambdalisue/rms2dfinder
Author: Alisue
Author-email: lambdalisue@hashnote.net
License: MIT
Download-URL: https://github.com/lambdalisue/rms2dfinder/tarball/master
Keywords: utility Amber rms2d molecular dynamics
Platform: UNKNOWN
Classifier: Development Status :: 3 - Alpha
Classifier: Intended Audience :: Developers
Classifier: License :: OSI Approved :: MIT License
Classifier: Programming Language :: Python
Classifier: Programming Language :: Python :: 2.6
Classifier: Programming Language :: Python :: 2.7
